my_module/__init__.py
my_module/choropleth_maps.py
my_module/data_cleaning.py
my_module/data_grouping.py
my_module/data_processing.py
my_module/state_analysis.py
my_module/temporal_analysis.py
my_module/utils.py
tests/__init__.py
tests/test_data_cleaning.py
tests/test_data_grouping.py
tests/test_data_processing.py
tests/test_state_analysis.py
tests/test_temporal_analysis.py
activity_4_entrega_Programacion_Ciencia_de_datos-0.1.3.dist-info/LICENCE
activity_4_entrega_Programacion_Ciencia_de_datos-0.1.3.dist-info/METADATA
activity_4_entrega_Programacion_Ciencia_de_datos-0.1.3.dist-info/WHEEL
activity_4_entrega_Programacion_Ciencia_de_datos-0.1.3.dist-info/entry_points.txt
activity_4_entrega_Programacion_Ciencia_de_datos-0.1.3.dist-info/top_level.txt
activity_4_entrega_Programacion_Ciencia_de_datos-0.1.3.dist-info/RECORD
